README.rst
ez_setup.py
setup.py
django_simple_webservice.egg-info/PKG-INFO
django_simple_webservice.egg-info/SOURCES.txt
django_simple_webservice.egg-info/dependency_links.txt
django_simple_webservice.egg-info/requires.txt
django_simple_webservice.egg-info/top_level.txt
simple_webservice/__init__.py
simple_webservice/calls.py
simple_webservice/core.py
simple_webservice/serializer.py
simple_webservice/urls.py
simple_webservice/views.py