Metadata-Version: 1.1
Name: django-simple-webservice
Version: 0.1.1
Summary: Django app for simple create  json-rpc like webservices
Home-page: https://bitbucket.org/liricus/django-simple-webservice
Author: Liricus SRL
Author-email: info@liricus.com.ar
License: LGPL
Keywords: webservices json simple django
Platform: UNKNOWN
Classifier: Development Status :: 4 - Beta
Classifier: Environment :: Web Environment
Classifier: Framework :: Django
Classifier: Intended Audience :: Developers
Classifier: License :: OSI Approved :: BSD License
Classifier: Programming Language :: Python
Classifier: Programming Language :: Python :: 2
Classifier: Programming Language :: Python :: 2.7
Classifier: License :: OSI Approved :: GNU Library or Lesser General Public License (LGPL)
Classifier: Topic :: Software Development :: Libraries :: Application Frameworks
